liboidcagent/__init__.py
liboidcagent/liboidcagent.py
liboidcagent-0.6.0.dist-info/LICENSE
liboidcagent-0.6.0.dist-info/METADATA
liboidcagent-0.6.0.dist-info/WHEEL
liboidcagent-0.6.0.dist-info/top_level.txt
liboidcagent-0.6.0.dist-info/RECORD
