Metadata-Version: 2.1
Name: liboidcagent
Version: 0.6.0
Summary: A python library for requesting OpenID Connect access tokens from oidc-agent.
Home-page: https://github.com/indigo-dc/liboidc-agent-py
Author: Gabriel Zachmann
Author-email: oidc-agent-contact@lists.kit.edu
License: MIT
Project-URL: Source, https://github.com/indigo-dc/liboidc-agent-py
Project-URL: Bug Tracker, https://github.com/indigo-dc/liboidc-agent-py/issues
Project-URL: Documentation, https://indigo-dc.gitbooks.io/oidc-agent/api-py.html
Classifier: License :: OSI Approved :: MIT License
Classifier: Programming Language :: Python
Classifier: Programming Language :: Python :: 3
Classifier: Programming Language :: Python :: 3.4
Classifier: Programming Language :: Python :: 3.5
Classifier: Programming Language :: Python :: 3.6
Classifier: Programming Language :: Python :: 3.7
Classifier: Programming Language :: Python :: 3.8
Classifier: Programming Language :: Python :: 3.9
Classifier: Programming Language :: Python :: 3.10
Classifier: Operating System :: Unix
Classifier: Topic :: System :: Systems Administration :: Authentication/Directory
Classifier: Topic :: Utilities
Classifier: Topic :: Security
Classifier: Topic :: Software Development :: Libraries
Classifier: Intended Audience :: Developers
Classifier: Intended Audience :: Information Technology
Classifier: Intended Audience :: Science/Research
Classifier: Intended Audience :: System Administrators
Classifier: Environment :: Console
Classifier: Natural Language :: English
License-File: LICENSE
Requires-Dist: PyNaCl >=1.2.0
